fbenum-1.0.1.dist-info/METADATA
fbenum-1.0.1.dist-info/WHEEL
fbenum-1.0.1.dist-info/licenses/LICENSE
fbenum/__init__.py
fbenum/adapter.py
fbenum/enum.py
fbenum-1.0.1.dist-info/RECORD
