Metadata-Version: 2.1
Name: fbenum
Version: 1.0.1
Summary: Library provides fallback enum functionality. Fully compatible with pydantic.
Keywords: enum pydantic
Author-Email: Vadim Suharnikov <vsuharnikov@gmail.com>
License: MIT
Requires-Python: >=3.12
Requires-Dist: pydantic-core>=2.14.6
